README
example.py
servable.py
setup.py
test.py
servable.egg-info/PKG-INFO
servable.egg-info/SOURCES.txt
servable.egg-info/dependency_links.txt
servable.egg-info/top_level.txt
simplejson/__init__.py
simplejson/decoder.py
simplejson/encoder.py
simplejson/scanner.py
simplejson/tool.py